asiga/__init__.py
asiga/__main__.py
asiga/scraper.py
ucsdasiga-1.0.0a7.dist-info/LICENSE
ucsdasiga-1.0.0a7.dist-info/METADATA
ucsdasiga-1.0.0a7.dist-info/WHEEL
ucsdasiga-1.0.0a7.dist-info/top_level.txt
ucsdasiga-1.0.0a7.dist-info/RECORD
