Metadata-Version: 2.1
Name: ucsdasiga
Version: 1.0.0a7
Summary: A simple API wrapper and web scraper for the UCSD Associated Students (AS) instructor grade archive.
Author-email: Jacob Lee <Jacob.J.Lee@outlook.com>
License: MIT License
Project-URL: homepage, https://github.com/JacobLee23/UCSD-AS-One
Classifier: Development Status :: 3 - Alpha
Classifier: License :: OSI Approved :: MIT License
Classifier: Natural Language :: English
Classifier: Operating System :: OS Independent
Classifier: Programming Language :: Python
Classifier: Programming Language :: Python :: 3
Classifier: Programming Language :: Python :: 3.8
Classifier: Programming Language :: Python :: 3.9
Classifier: Programming Language :: Python :: 3.10
Classifier: Programming Language :: Python :: 3.11
Requires-Python: >=3.8
License-File: LICENSE
Requires-Dist: lxml (==4.9.2)
Requires-Dist: pandas (==2.0.3)
Requires-Dist: pytz (==2023.3)
Requires-Dist: requests (==2.31.0)
Requires-Dist: charset-normalizer (==3.1.0) ; python_full_version >= "3.7.0"
Requires-Dist: tzdata (==2023.3) ; python_version >= "2"
Requires-Dist: python-dateutil (==2.8.2) ; python_version >= "2.7" and python_version not in "3.0, 3.1, 3.2"
Requires-Dist: six (==1.16.0) ; python_version >= "2.7" and python_version not in "3.0, 3.1, 3.2"
Requires-Dist: numpy (==1.25.0) ; python_version >= "3.10"
Requires-Dist: idna (==3.4) ; python_version >= "3.5"
Requires-Dist: certifi (==2023.5.7) ; python_version >= "3.6"
Requires-Dist: urllib3 (==2.0.3) ; python_version >= "3.7"
